{
  "application-methods": [
    {
      "content": "Dans mes candidatures, j'ai repris des **mots clefs** utilisés par l'employeur",
      "goalId": "application-keywords"
    },
    {
      "content": "J'ai identifié **3 points faibles sur mon CV** qui pourraient inquiéter un recruteur",
      "goalId": "resume-awareness"
    },
    {
      "content": "Je sais comment **mieux tourner** les points faibles de mon CV",
      "goalId": "resume-pimp"
    },
    {
      "content": "J'ai fait **relire** mon CV et lettre de motivation par quelqu'un en qui j'ai **confiance**",
      "goalId": "resume-readover"
    }
  ],
  "application-methods-to-interview": [
    {
      "content": "J'ai vérifié que mon CV inclut une liste de mes **compétences**",
      "goalId": "CV-skills-list"
    },
    {
      "content": "J'ai personnalisé **à fond** chacune de mes candidatures selon les **attentes** de l'employeur",
      "goalId": "personalised-applications"
    },
    {
      "content": "J'ai identifié **3 points faibles sur mon CV** qui pourraient inquiéter un recruteur",
      "goalId": "resume-awareness"
    },
    {
      "content": "Je sais comment **mieux tourner** les points faibles de mon CV",
      "goalId": "resume-pimp"
    },
    {
      "content": "J'ai fait **relire** mon CV et lettre de motivation par quelqu'un en qui j'ai **confiance**",
      "goalId": "resume-readover"
    }
  ],
  "apply-in-unliked-job": [
    {
      "content": "Dans mes candidatures, j'ai repris des **mots clefs** utilisés par l'employeur",
      "goalId": "application-keywords"
    },
    {
      "content": "J'ai identifié **3 points faibles sur mon CV** qui pourraient inquiéter un recruteur",
      "goalId": "resume-awareness"
    },
    {
      "content": "Je sais comment **mieux tourner** les points faibles de mon CV",
      "goalId": "resume-pimp"
    },
    {
      "content": "J'ai fait **relire** mon CV et lettre de motivation par quelqu'un en qui j'ai **confiance**",
      "goalId": "resume-readover"
    },
    {
      "content": "Je connais **3 postes** qui recrutent **plus**",
      "goalId": "better-jobs-awareness"
    }
  ],
  "confidence-boost": [
    {
      "content": "J'ai fait une liste de **3** de mes réussites",
      "goalId": "achievement-awareness"
    },
    {
      "content": "Je sais que je suis dans le **top 15%** de personnes sur Bob qui ont des chances de trouver un poste bientôt",
      "goalId": "comparative-boost"
    },
    {
      "content": "J'arrive à **accepter** que certaines journées sont moins efficaces que d'autres, sans **m'en vouloir**",
      "goalId": "accept-myself"
    },
    {
      "content": "J'ai pris du temps pour **moi**",
      "goalId": "self-care"
    }
  ],
  "diploma-free-job": [
    {
      "content": "J'ai adapté mon **CV** pour **cibler** un métier qui **recrute** beaucoup dans mon département",
      "goalId": "diploma-free-application"
    },
    {
      "content": "J'ai considéré la possibilité de trouver un **job alimentaire** pendant ma recherche d'emploi",
      "goalId": "alimentary-job-for-search"
    },
    {
      "content": "J'ai comparé les différences de **salaire** entre les métiers **avec** et **sans** diplôme",
      "goalId": "diploma-salary-impact"
    }
  ],
  "get-alternance": [
    {
      "content": "J'ai obtenu un **entretien d'embauche** avant de me fixer sur une formation",
      "goalId": "interview-before-training-centre"
    },
    {
      "content": "J'ai une idée de ma **rémunération** et de son impact sur mon quotidien ",
      "goalId": "alternance-pay"
    },
    {
      "content": "J'ai signé un contrat en alternance",
      "goalId": "alternance-started"
    },
    {
      "content": "J'ai vérifié qu'il y a **besoin** d'obtenir un diplôme pour ce poste",
      "goalId": "check-diploma"
    },
    {
      "content": "J'ai **regardé les statistiques** pour confirmer qu'il y a du travail dans ce métier",
      "goalId": "check-market"
    }
  ],
  "get-diploma": [
    {
      "content": "J'ai préparé **5 questions** à poser à des centres de formation ",
      "goalId": "training-centre-questions"
    },
    {
      "content": "J'ai demandé au centre de formation de me mettre en contact avec **3 anciens élèves**",
      "goalId": "training-centre-alumni"
    },
    {
      "content": "J'ai **3 arguments pour évaluer mon projet** avec mon conseiller emploi",
      "goalId": "employment-service-biais"
    },
    {
      "content": "J'ai vérifié qu'il y a **besoin** d'obtenir un diplôme pour ce poste",
      "goalId": "check-diploma"
    },
    {
      "content": "J'ai **regardé les statistiques** pour confirmer qu'il y a du travail dans ce métier",
      "goalId": "check-market"
    },
    {
      "content": "J'ai pu **poser des questions directement** à quelqu'un qui fait **ce métier**",
      "goalId": "network-contact"
    }
  ],
  "interview-success": [
    {
      "content": "J'arrive à présenter à l'oral mon **parcours** en 2 minutes",
      "goalId": "elevator-pitch"
    },
    {
      "content": "J'arrive à présenter à l'oral mes **qualités** en 2 minutes",
      "goalId": "competences-pitch"
    },
    {
      "content": "J'ai regardé la vidéo sur le **langage corporel** pour préparer mes entretiens",
      "goalId": "body-language-video"
    },
    {
      "content": "J'ai fait un entrainement pour mes entretiens avec quelqu'un qui connait ce métier",
      "goalId": "interview-practice"
    },
    {
      "content": "Pour chacune de mes qualités, j'ai trouvé un **exemple concret** de quelque chose que j'ai **réalisée**",
      "goalId": "examples-for-interview"
    }
  ],
  "likeable-job": [
    {
      "content": "J'ai trouvé **3 idées de métiers** qui me donnent envie d'en savoir plus",
      "goalId": "desire-for-jobs"
    },
    {
      "content": "Je connais **3 métiers** qui pourraient convenir à ma **personnalité**",
      "goalId": "jobs-that-fit"
    },
    {
      "content": "J'ai investi de mon temps pour **mieux connaître** un métier",
      "goalId": "active-immersion"
    }
  ],
  "motivate-in-job": [
    {
      "content": "J'arrive à **identifier ce qui me plait ou non** dans ce métier",
      "goalId": "job-awareness"
    },
    {
      "content": "J'ai pris du temps pour **moi**",
      "goalId": "self-care"
    },
    {
      "content": "J'ai discuté avec **quelqu'un qui fait ce métier**",
      "goalId": "network-motivation"
    }
  ],
  "other-leads": [
    {
      "content": "Je connais **3 villes** où il y a **moins de concurrence**",
      "goalId": "better-cities-awareness"
    },
    {
      "content": "J'ai commencé à postuler dans des **villes** où **la concurrence est plus faible**",
      "goalId": "better-cities-apply"
    },
    {
      "content": "Je connais **3 métiers** où il y a **moins de concurrence**",
      "goalId": "better-jobs-awareness"
    },
    {
      "content": "J'ai considéré la possibilité de **changer de métier**",
      "goalId": "consider-other-jobs"
    },
    {
      "content": "J'ai pris en compte ce qu'un changement signifierait **pour mes proches**",
      "goalId": "impact-on-entourage"
    },
    {
      "content": " J'ai commencé une **réorientation professionnelle** vers un de ces métiers",
      "goalId": "start-reorienting"
    }
  ],
  "presearch-methods": [
    {
      "content": "Je sais dans quels **secteurs** mon métier offre des **opportunités**",
      "goalId": "other-sectors-awareness"
    },
    {
      "content": "J'ai assisté à **2 évènements** en lien avec mon métier ",
      "goalId": "events-attended"
    },
    {
      "content": "J'ai pris contact avec un groupe ou une association pour **me faire accompagner**",
      "goalId": "association-contact"
    },
    {
      "content": "J'ai pu **poser des questions directement** à quelqu'un qui fait **ce métier**",
      "goalId": "network-contact"
    },
    {
      "content": "Je connais **3 personnes dans mon secteur** que je pourrais contacter",
      "goalId": "network-list"
    }
  ],
  "targeted-search": [
    {
      "content": "J'ai discuté avec **quelqu'un qui fait ce métier**",
      "goalId": "network-motivation"
    },
    {
      "content": "J'ai trouvé des informations sur **comment** les autres trouvent du travail dans mon métier ",
      "goalId": "targeted-insights"
    },
    {
      "content": "Je m'organise pour passer plus de temps à postuler avec la méthode de recherche qui **marche le mieux**",
      "goalId": "targeted-time-spent"
    },
    {
      "content": "J'ai envoyé une candidature par un moyen (réseau, candidature spontanée) que je n'avais pas encore **essayé**",
      "goalId": "targeted-done"
    }
  ],
  "try-without-diploma": [
    {
      "content": "Dans mes candidatures, j'ai repris des **mots clefs** utilisés par l'employeur",
      "goalId": "application-keywords"
    },
    {
      "content": "J'ai identifié **3 points faibles sur mon CV** qui pourraient inquiéter un recruteur",
      "goalId": "resume-awareness"
    },
    {
      "content": "Je sais comment **mieux tourner** les points faibles de mon CV",
      "goalId": "resume-pimp"
    },
    {
      "content": "J'ai fait **relire** mon CV et lettre de motivation par quelqu'un en qui j'ai **confiance**",
      "goalId": "resume-readover"
    },
    {
      "content": "J'ai pu **poser des questions directement** à quelqu'un qui fait **ce métier**",
      "goalId": "network-contact"
    },
    {
      "content": "Je connais **3 personnes dans mon secteur** que je pourrais contacter",
      "goalId": "network-list"
    }
  ]
}
