[
 {
  "_id": "recwWA7VmdP241IAz",
  "_order": 0,
  "actionId": "recwWA7VmdP241IAz",
  "scoreByChallenge": {}
 },
 {
  "_id": "recXIxb0OryCywm9M",
  "_order": 1,
  "actionId": "recXIxb0OryCywm9M",
  "scoreByChallenge": {}
 },
 {
  "_id": "recbnwltuaQRYOu9d",
  "_order": 2,
  "actionId": "recbnwltuaQRYOu9d",
  "scoreByChallenge": {}
 },
 {
  "_id": "recHLNI34GbcrfLEU",
  "_order": 3,
  "actionId": "recHLNI34GbcrfLEU",
  "scoreByChallenge": {}
 },
 {
  "_id": "recnHHdsSXPMxVkJh",
  "_order": 4,
  "actionId": "recnHHdsSXPMxVkJh",
  "scoreByChallenge": {}
 },
 {
  "_id": "rec8tlCRVcCGp6zcW",
  "_order": 5,
  "actionId": "rec8tlCRVcCGp6zcW",
  "scoreByChallenge": {}
 },
 {
  "_id": "recf9AV8Ye3YLboEx",
  "_order": 6,
  "actionId": "recf9AV8Ye3YLboEx",
  "scoreByChallenge": {}
 },
 {
  "_id": "recmVoVTl01eqPKRx",
  "_order": 7,
  "actionId": "recmVoVTl01eqPKRx",
  "scoreByChallenge": {}
 },
 {
  "_id": "recSDP31CmR7IxG7b",
  "_order": 8,
  "actionId": "recSDP31CmR7IxG7b",
  "scoreByChallenge": {}
 },
 {
  "_id": "recsryO90PG3xiiAu",
  "_order": 9,
  "actionId": "recsryO90PG3xiiAu",
  "scoreByChallenge": {}
 },
 {
  "_id": "rec85bAHk8dCVjpzG",
  "_order": 10,
  "actionId": "rec85bAHk8dCVjpzG",
  "scoreByChallenge": {}
 },
 {
  "_id": "rec9J04N7SPypSHdY",
  "_order": 11,
  "actionId": "rec9J04N7SPypSHdY",
  "scoreByChallenge": {}
 },
 {
  "_id": "rec8mlXD7k0xAdmWg",
  "_order": 12,
  "actionId": "rec8mlXD7k0xAdmWg",
  "scoreByChallenge": {}
 },
 {
  "_id": "recjp9JT3GUf5z5XE",
  "_order": 13,
  "actionId": "recjp9JT3GUf5z5XE",
  "scoreByChallenge": {}
 }
]
